weather/__init__.py
weather/get_reading.py
weather/show_reading.py
halaloyamora-1.0.0.dist-info/METADATA
halaloyamora-1.0.0.dist-info/WHEEL
halaloyamora-1.0.0.dist-info/top_level.txt
halaloyamora-1.0.0.dist-info/RECORD
